lazygrid/__init__.py
lazygrid/config.py
lazygrid/database.py
lazygrid/datasets.py
lazygrid/grid.py
lazygrid/lazy_estimator.py
lazygrid/plotter.py
lazygrid/statistics.md
lazygrid/statistics.py
lazygrid-5.0.6.dist-info/LICENSE.txt
lazygrid-5.0.6.dist-info/METADATA
lazygrid-5.0.6.dist-info/WHEEL
lazygrid-5.0.6.dist-info/top_level.txt
lazygrid-5.0.6.dist-info/RECORD
