Metadata-Version: 2.1
Name: lazygrid
Version: 5.0.6
Summary: LazyGrid: Automatic, efficient and flexible implementation of complex machine learning pipeline generation and cross-validation.
Home-page: https://github.com/glubbdubdrib/lazygrid
Author: Pietro Barbiero and Giovanni Squillero
Author-email: cleisthenes.megacleos@gmail.com
License: Apache 2.0
Platform: UNKNOWN
